congress_wrapper/__init__.py
congress_wrapper/example.py
congress_wrapper-0.0.1.dist-info/METADATA
congress_wrapper-0.0.1.dist-info/WHEEL
congress_wrapper-0.0.1.dist-info/licenses/LICENSE
congress_wrapper-0.0.1.dist-info/RECORD
