Metadata-Version: 2.3
Name: congress-wrapper
Version: 0.0.1
Summary: Python wrapper for https://gpo.congress.gov/
Project-URL: Homepage, https://github.com/CtrlAltDeplete/congress-wrapper
Project-URL: Issues, https://github.com/CtrlAltDeplete/congress-wrapper/issues
Author-email: CtrlAltDeplete <gavyn@ctrlaltdeplete.com>
License: Copyright (c) 2018 The Python Packaging Authority
License-File: LICENSE
Classifier: License :: OSI Approved :: MIT License
Classifier: Operating System :: OS Independent
Classifier: Programming Language :: Python :: 3
Requires-Python: >=3.12
